[
  {
    "ContainingType": "Beekepeer.Controllers.AutomovilController",
    "Method": "Delete",
    "RelativePath": "api/Automovil/delete/{id}",
    "HttpMethod": "DELETE",
    "IsController": true,
    "Order": 0,
    "Parameters": [
      {
        "Name": "id",
        "Type": "System.Int32",
        "IsRequired": true
      }
    ],
    "ReturnTypes": []
  },
  {
    "ContainingType": "Beekepeer.Controllers.AutomovilController",
    "Method": "GetById",
    "RelativePath": "api/Automovil/getById/{id}",
    "HttpMethod": "GET",
    "IsController": true,
    "Order": 0,
    "Parameters": [
      {
        "Name": "id",
        "Type": "System.Int32",
        "IsRequired": true
      }
    ],
    "ReturnTypes": []
  },
  {
    "ContainingType": "Beekepeer.Controllers.AutomovilController",
    "Method": "GetAutomovil",
    "RelativePath": "api/Automovil/getListAutomovil",
    "HttpMethod": "GET",
    "IsController": true,
    "Order": 0,
    "Parameters": [],
    "ReturnTypes": [
      {
        "Type": "System.Collections.Generic.List\u00601[[Beekepeer.Model.automovilClass, Beekepeer, Version=1.0.0.0, Culture=neutral, PublicKeyToken=null]]",
        "MediaTypes": [
          "text/plain",
          "application/json",
          "text/json"
        ],
        "StatusCode": 200
      }
    ]
  },
  {
    "ContainingType": "Beekepeer.Controllers.AutomovilController",
    "Method": "Insertar",
    "RelativePath": "api/Automovil/insert",
    "HttpMethod": "POST",
    "IsController": true,
    "Order": 0,
    "Parameters": [
      {
        "Name": "nuevoAuto",
        "Type": "Beekepeer.Model.automovilClass",
        "IsRequired": true
      }
    ],
    "ReturnTypes": []
  },
  {
    "ContainingType": "Beekepeer.Controllers.AutomovilController",
    "Method": "Search",
    "RelativePath": "api/Automovil/search",
    "HttpMethod": "GET",
    "IsController": true,
    "Order": 0,
    "Parameters": [
      {
        "Name": "marca",
        "Type": "System.String",
        "IsRequired": false
      },
      {
        "Name": "modelo",
        "Type": "System.String",
        "IsRequired": false
      }
    ],
    "ReturnTypes": []
  },
  {
    "ContainingType": "Beekepeer.Controllers.AutomovilController",
    "Method": "UpdateMarca",
    "RelativePath": "api/Automovil/updateMarca/{id}",
    "HttpMethod": "PATCH",
    "IsController": true,
    "Order": 0,
    "Parameters": [
      {
        "Name": "id",
        "Type": "System.Int32",
        "IsRequired": true
      },
      {
        "Name": "nuevaMarca",
        "Type": "System.String",
        "IsRequired": true
      }
    ],
    "ReturnTypes": []
  },
  {
    "ContainingType": "Beekepeer.Controllers.AutomovilController",
    "Method": "UpdateModelo",
    "RelativePath": "api/Automovil/updateModelo/{id}",
    "HttpMethod": "PATCH",
    "IsController": true,
    "Order": 0,
    "Parameters": [
      {
        "Name": "id",
        "Type": "System.Int32",
        "IsRequired": true
      },
      {
        "Name": "nuevoModelo",
        "Type": "System.String",
        "IsRequired": true
      }
    ],
    "ReturnTypes": []
  }
]